accum.sv
module accum #(parameter BITS=8)
(
    input  wire             i_ld,
    input  wire [BITS-1:0]  i_data,
    output wire [BITS-1:0]  o_data,
    output wire             o_zero
);

reg [BITS-1:0] value;

initial value = 0;

always_latch begin
    if(i_ld) begin
        assign value = i_data;
    end
end

assign o_zero = (value == 0) ? 1 : 0;
assign o_data = value;
    
endmodule

wv_accum.vcd
$version Generated by VerilatedVcd $end
$date Mon Apr 22 15:06:12 2024
 $end
$timescale   1ps $end

 $scope module TOP $end
  $var wire  8 $ i_data [7:0] $end
  $var wire  1 # i_ld $end
  $var wire  8 % o_data [7:0] $end
  $var wire  1 & o_zero $end
  $scope module accum $end
   $var wire 32 ( BITS [31:0] $end
   $var wire  8 $ i_data [7:0] $end
   $var wire  1 # i_ld $end
   $var wire  8 % o_data [7:0] $end
   $var wire  1 & o_zero $end
   $var wire  8 ' value [7:0] $end
  $upscope $end
 $upscope $end
$enddefinitions $end


#0
0#
b01101001 $
b00000000 %
1&
b00000000 '
b00000000000000000000000000001000 (
#1
#2
#3
#4
#5
#6
#7
#8
#9
#10
#11
#12
#13
#14
#15
#16
b01101010 $
#17
#18
#19
#20
#21
#22
#23
#24
#25
#26
#27
#28
#29
#30
#31
1#
b01101010 %
0&
b01101010 '
#32
0#
#33
#34
b11111111 $
#35
#36
1#
b11111111 %
b11111111 '
#37
0#
#38
b11110010 $
