accum.sv
module accum #(parameter BITS=8)
(
    input  wire             i_clk,
    input  wire             i_ld,
    input  wire [BITS-1:0]  i_data,
    output wire [BITS-1:0]  o_data,
    output wire             o_zero
);

reg [BITS-1:0] value;

initial value = 0;

always @(posedge i_clk) begin
    if(i_ld) begin
        value <= i_data;
    end    
end 

assign o_zero = (value == 0) ? 1 : 0;
assign o_data = value;
    
endmodule

wv_accum.vcd
$version Generated by VerilatedVcd $end
$date Sun Apr 28 17:24:05 2024
 $end
$timescale   1ps $end

 $scope module TOP $end
  $var wire  1 # i_clk $end
  $var wire  8 % i_data [7:0] $end
  $var wire  1 $ i_ld $end
  $var wire  8 & o_data [7:0] $end
  $var wire  1 ' o_zero $end
  $scope module accum $end
   $var wire 32 ) BITS [31:0] $end
   $var wire  1 # i_clk $end
   $var wire  8 % i_data [7:0] $end
   $var wire  1 $ i_ld $end
   $var wire  8 & o_data [7:0] $end
   $var wire  1 ' o_zero $end
   $var wire  8 ( value [7:0] $end
  $upscope $end
 $upscope $end
$enddefinitions $end


#0
1#
0$
b01101001 %
b00000000 &
1'
b00000000 (
b00000000000000000000000000001000 )
#1
0#
#2
1#
#3
0#
#4
1#
#5
0#
#6
1#
#7
0#
#8
1#
#9
0#
#10
1#
#11
0#
#12
1#
#13
0#
#14
1#
#15
0#
#16
1#
b01101010 %
#17
0#
#18
1#
#19
0#
#20
1#
#21
0#
#22
1#
#23
0#
#24
1#
#25
0#
#26
1#
#27
0#
#28
1#
#29
0#
#30
1#
#31
0#
1$
#32
1#
b01101010 &
0'
b01101010 (
#33
0#
0$
#34
1#
b11111111 %
#35
0#
#36
1#
1$
b11111111 &
b11111111 (
#37
0#
0$
#38
1#
b11110010 %
