register.sv
module register #(parameter BITS = 16) (
    input  wire            i_ld, 
    input  wire [BITS-1:0] i_data, 
    output wire [BITS-1:0] o_data
);

reg [BITS-1:0] value;

initial value <= 0;

always @(*) begin
    if(i_ld) value <= i_data;    
end    

assign o_data = value;

endmodule

wv_register.vcd
$version Generated by VerilatedVcd $end
$timescale 1ps $end
 $scope module TOP $end
  $var wire 1 # i_ld $end
  $var wire 16 $ i_data [15:0] $end
  $var wire 16 % o_data [15:0] $end
  $scope module register $end
   $var wire 32 ' BITS [31:0] $end
   $var wire 1 # i_ld $end
   $var wire 16 $ i_data [15:0] $end
   $var wire 16 % o_data [15:0] $end
   $var wire 16 & value [15:0] $end
  $upscope $end
 $upscope $end
$enddefinitions $end


#0
0#
b0000000000000000 $
b0000000000000000 %
b0000000000000000 &
b00000000000000000000000000010000 '
#1
b0000000000000001 $
#2
b0000000000000010 $
#3
b0000000000000011 $
#4
b0000000000000100 $
#5
b0000000000000101 $
#6
1#
b0000000000000110 $
b0000000000000110 %
b0000000000000110 &
#7
0#
b0000000000000111 $
#8
b0000000000001000 $
#9
b0000000000001001 $
#10
b0000000000001010 $
#11
b0000000000001011 $
#12
b0000000000001100 $
#13
b0000000000001101 $
#14
b0000000000001110 $
#15
b0000000000001111 $
#16
b0000000000010000 $
#17
b0000000000010001 $
#18
b0000000000010010 $
#19
b0000000000010011 $
#20
b0000000000010100 $
#21
b0000000000010101 $
#22
b0000000000010110 $
#23
b0000000000010111 $
#24
b0000000000011000 $
#25
b0000000000011001 $
#26
b0000000000011010 $
#27
b0000000000011011 $
#28
b0000000000011100 $
#29
b0000000000011101 $
#30
b0000000000011110 $
#31
b0000000000011111 $
#32
b0000000000100000 $
#33
b0000000000100001 $
#34
b0000000000100010 $
#35
b0000000000100011 $
#36
b0000000000100100 $
#37
b0000000000100101 $
#38
b0000000000100110 $
#39
b0000000000100111 $
#40
b0000000000101000 $
#41
b0000000000101001 $
#42
b0000000000101010 $
#43
b0000000000101011 $
#44
b0000000000101100 $
#45
b0000000000101101 $
#46
b0000000000101110 $
#47
b0000000000101111 $
#48
b0000000000110000 $
#49
b0000000000110001 $
#50
b0000000000110010 $
#51
b0000000000110011 $
#52
b0000000000110100 $
#53
b0000000000110101 $
#54
b0000000000110110 $
#55
b0000000000110111 $
#56
b0000000000111000 $
#57
b0000000000111001 $
#58
b0000000000111010 $
#59
b0000000000111011 $
#60
b0000000000111100 $
#61
b0000000000111101 $
#62
b0000000000111110 $
#63
b0000000000111111 $
#64
b0000000001000000 $
#65
b0000000001000001 $
#66
b0000000001000010 $
#67
b0000000001000011 $
#68
b0000000001000100 $
#69
b0000000001000101 $
#70
b0000000001000110 $
#71
b0000000001000111 $
#72
b0000000001001000 $
#73
b0000000001001001 $
#74
b0000000001001010 $
#75
b0000000001001011 $
#76
b0000000001001100 $
#77
b0000000001001101 $
#78
b0000000001001110 $
#79
b0000000001001111 $
#80
b0000000001010000 $
#81
b0000000001010001 $
#82
b0000000001010010 $
#83
b0000000001010011 $
#84
b0000000001010100 $
#85
b0000000001010101 $
#86
b0000000001010110 $
#87
b0000000001010111 $
#88
b0000000001011000 $
#89
b0000000001011001 $
#90
b0000000001011010 $
#91
b0000000001011011 $
#92
b0000000001011100 $
#93
b0000000001011101 $
#94
b0000000001011110 $
#95
b0000000001011111 $
#96
b0000000001100000 $
#97
b0000000001100001 $
#98
b0000000001100010 $
#99
b0000000001100011 $
#100
b0000000001100100 $
#101
b0000000001100101 $
#102
b0000000001100110 $
#103
b0000000001100111 $
#104
b0000000001101000 $
#105
b0000000001101001 $
#106
b0000000001101010 $
#107
b0000000001101011 $
#108
b0000000001101100 $
#109
b0000000001101101 $
#110
b0000000001101110 $
#111
b0000000001101111 $
#112
b0000000001110000 $
#113
b0000000001110001 $
#114
b0000000001110010 $
#115
b0000000001110011 $
#116
b0000000001110100 $
#117
b0000000001110101 $
#118
b0000000001110110 $
#119
b0000000001110111 $
#120
b0000000001111000 $
#121
b0000000001111001 $
#122
b0000000001111010 $
#123
b0000000001111011 $
#124
b0000000001111100 $
#125
b0000000001111101 $
#126
b0000000001111110 $
#127
b0000000001111111 $
#128
b0000000010000000 $
#129
b0000000010000001 $
#130
b0000000010000010 $
#131
b0000000010000011 $
#132
b0000000010000100 $
#133
b0000000010000101 $
#134
b0000000010000110 $
#135
b0000000010000111 $
#136
b0000000010001000 $
#137
b0000000010001001 $
#138
b0000000010001010 $
#139
b0000000010001011 $
#140
b0000000010001100 $
#141
b0000000010001101 $
#142
b0000000010001110 $
#143
b0000000010001111 $
#144
b0000000010010000 $
#145
b0000000010010001 $
#146
b0000000010010010 $
#147
b0000000010010011 $
#148
b0000000010010100 $
#149
b0000000010010101 $
#150
b0000000010010110 $
#151
b0000000010010111 $
#152
b0000000010011000 $
#153
b0000000010011001 $
#154
b0000000010011010 $
#155
b0000000010011011 $
#156
b0000000010011100 $
#157
b0000000010011101 $
#158
b0000000010011110 $
#159
b0000000010011111 $
#160
b0000000010100000 $
#161
b0000000010100001 $
#162
b0000000010100010 $
#163
b0000000010100011 $
#164
b0000000010100100 $
#165
b0000000010100101 $
#166
b0000000010100110 $
#167
b0000000010100111 $
#168
b0000000010101000 $
#169
b0000000010101001 $
#170
b0000000010101010 $
#171
b0000000010101011 $
#172
b0000000010101100 $
#173
b0000000010101101 $
#174
b0000000010101110 $
#175
b0000000010101111 $
#176
b0000000010110000 $
#177
b0000000010110001 $
#178
b0000000010110010 $
#179
b0000000010110011 $
#180
b0000000010110100 $
#181
b0000000010110101 $
#182
b0000000010110110 $
#183
b0000000010110111 $
#184
b0000000010111000 $
#185
b0000000010111001 $
#186
b0000000010111010 $
#187
b0000000010111011 $
#188
b0000000010111100 $
#189
b0000000010111101 $
#190
b0000000010111110 $
#191
b0000000010111111 $
#192
b0000000011000000 $
#193
b0000000011000001 $
#194
b0000000011000010 $
#195
b0000000011000011 $
#196
b0000000011000100 $
#197
b0000000011000101 $
#198
b0000000011000110 $
#199
b0000000011000111 $
#200
b0000000011001000 $
#201
b0000000011001001 $
#202
b0000000011001010 $
#203
b0000000011001011 $
#204
b0000000011001100 $
#205
b0000000011001101 $
#206
b0000000011001110 $
#207
b0000000011001111 $
#208
b0000000011010000 $
#209
b0000000011010001 $
#210
b0000000011010010 $
#211
b0000000011010011 $
#212
b0000000011010100 $
#213
b0000000011010101 $
#214
b0000000011010110 $
#215
b0000000011010111 $
#216
b0000000011011000 $
#217
b0000000011011001 $
#218
b0000000011011010 $
#219
b0000000011011011 $
#220
b0000000011011100 $
#221
b0000000011011101 $
#222
b0000000011011110 $
#223
b0000000011011111 $
#224
b0000000011100000 $
#225
b0000000011100001 $
#226
b0000000011100010 $
#227
b0000000011100011 $
#228
b0000000011100100 $
#229
b0000000011100101 $
#230
b0000000011100110 $
#231
b0000000011100111 $
#232
b0000000011101000 $
#233
b0000000011101001 $
#234
b0000000011101010 $
#235
b0000000011101011 $
#236
b0000000011101100 $
#237
b0000000011101101 $
#238
b0000000011101110 $
#239
b0000000011101111 $
#240
b0000000011110000 $
#241
b0000000011110001 $
#242
b0000000011110010 $
#243
b0000000011110011 $
#244
b0000000011110100 $
#245
b0000000011110101 $
#246
b0000000011110110 $
#247
b0000000011110111 $
#248
b0000000011111000 $
#249
b0000000011111001 $
#250
b0000000011111010 $
#251
b0000000011111011 $
#252
b0000000011111100 $
#253
b0000000011111101 $
#254
b0000000011111110 $
#255
b0000000011111111 $
#256
b0000000100000000 $
#257
b0000000100000001 $
#258
b0000000100000010 $
#259
b0000000100000011 $
#260
b0000000100000100 $
#261
b0000000100000101 $
#262
b0000000100000110 $
#263
b0000000100000111 $
#264
b0000000100001000 $
#265
b0000000100001001 $
#266
b0000000100001010 $
#267
b0000000100001011 $
#268
b0000000100001100 $
#269
b0000000100001101 $
#270
b0000000100001110 $
#271
b0000000100001111 $
#272
b0000000100010000 $
#273
b0000000100010001 $
#274
b0000000100010010 $
#275
b0000000100010011 $
#276
b0000000100010100 $
#277
b0000000100010101 $
#278
b0000000100010110 $
#279
b0000000100010111 $
#280
b0000000100011000 $
#281
b0000000100011001 $
#282
b0000000100011010 $
#283
b0000000100011011 $
#284
b0000000100011100 $
#285
b0000000100011101 $
#286
b0000000100011110 $
#287
b0000000100011111 $
#288
b0000000100100000 $
#289
b0000000100100001 $
#290
b0000000100100010 $
#291
b0000000100100011 $
#292
b0000000100100100 $
#293
b0000000100100101 $
#294
b0000000100100110 $
#295
b0000000100100111 $
#296
b0000000100101000 $
#297
b0000000100101001 $
#298
b0000000100101010 $
#299
b0000000100101011 $
